LICENSE
ceplib/__init__.py
ceplib/cep.py
ceplib/entities/__init__.py
ceplib/entities/cep_model.py
ceplib/errors/__init__.py
ceplib/errors/cep_invalid_character_error.py
ceplib/errors/cep_length_error.py
ceplib/errors/return_processing_error.py
ceplib/interfaces/__init__.py
ceplib/interfaces/service_interface.py
ceplib/interfaces/transform_interface.py
ceplib/interfaces/validation_interface.py
ceplib/loader/__init__.py
ceplib/loader/module_loader.py
ceplib/services/__init__.py
ceplib/services/awesomeapi/__init__.py
ceplib/services/awesomeapi/awesomeapi_config.py
ceplib/services/awesomeapi/awesomeapi_service.py
ceplib/services/cepla/__init__.py
ceplib/services/cepla/cepla_config.py
ceplib/services/cepla/cepla_service.py
ceplib/services/correios/__init__.py
ceplib/services/correios/correios_config.py
ceplib/services/correios/correios_service.py
ceplib/services/viacep/__init__.py
ceplib/services/viacep/viacep_config.py
ceplib/services/viacep/viacep_service.py
ceplib/transforms/__init__.py
ceplib/transforms/remove_non_digits.py
ceplib/transforms/zfill.py
ceplib/validations/__init__.py
ceplib/validations/cep_invalid_characters.py
ceplib/validations/cep_length.py
ceplib-0.1.2.dist-info/LICENSE
ceplib-0.1.2.dist-info/WHEEL
ceplib-0.1.2.dist-info/METADATA
ceplib-0.1.2.dist-info/RECORD
