Metadata-Version: 2.1
Name: ceplib
Version: 0.1.2
Summary: An easy way to fetch Brazil Zip code using several services
Home-page: https://github.com/erickod/CepLib
Author: Erick Duarte
Author-email: erickod@gmail.com
Requires-Python: >=3.9,<4.0
Classifier: Programming Language :: Python :: 3
Classifier: Programming Language :: Python :: 3.10
Classifier: Programming Language :: Python :: 3.9
Requires-Dist: httpx (>=0.22.0,<0.23.0)
Project-URL: Repository, https://github.com/erickod/CepLib
